ec/__init__.py
ec/__main__.py
ec/ec.py
ec/interface.py
ec/utils.py
ec/modules/__init__.py
ec/modules/classes.py
ec/modules/config.py
ec/modules/core.py
ec/modules/dispatch.py
ec/modules/exposed.py
ec/modules/helper_tasks.py
ec/modules/helpers.py
ec/modules/hooks.py
ec/modules/shell.py
ec/modules/state.py
ec/tools/__init__.py
ec/tools/delegator.py
ec/tools/injectDelegator.py
ec/types/__init__.py
ec/types/adv.py
ec/types/basics.py
ec/types/multi.py
ec/types/num.py
ec/types/path.py
ec/types/regex.py
ec-0.2.5.dist-info/AUTHORS.rst
ec-0.2.5.dist-info/LICENSE
ec-0.2.5.dist-info/METADATA
ec-0.2.5.dist-info/WHEEL
ec-0.2.5.dist-info/entry_points.txt
ec-0.2.5.dist-info/top_level.txt
ec-0.2.5.dist-info/RECORD
