Metadata-Version: 1.1
Name: ec
Version: 0.2.5
Summary: ec - a cli interface for python modules.
Home-page: https://github.com/Laufire/ec
Author: Laufire Technologies
Author-email: laufiretechnologies@gmail.com
License: MIT
Download-URL: https://pypi.python.org/pypi/ec
Keywords: ec command line cli interactive launch argument script dir shell dispatch decorator task arg group sub-commands type custom-type
Platform: any
Classifier: Development Status :: 2 - Pre-Alpha
Classifier: Environment :: Console
Classifier: Intended Audience :: Developers
Classifier: License :: OSI Approved :: MIT License
Classifier: Operating System :: OS Independent
Classifier: Natural Language :: English
Classifier: Programming Language :: Python :: 2.7
Classifier: Programming Language :: Python :: 3
Classifier: Programming Language :: Python :: 3.3
Classifier: Programming Language :: Python :: 3.4
Classifier: Topic :: Software Development
Classifier: Topic :: Utilities
